compmodel/compmodel.py
compartmentmodel-1.1.dist-info/METADATA
compartmentmodel-1.1.dist-info/WHEEL
compartmentmodel-1.1.dist-info/entry_points.txt
compartmentmodel-1.1.dist-info/top_level.txt
compartmentmodel-1.1.dist-info/RECORD
