Metadata-Version: 2.2
Name: compartmentModel
Version: 1.1
Summary: A command line utility to estimate parameters for Compartment Model. For more details see documentation and Dutta et al, Gen Res, 2023.
Home-page: https://github.com/guertinlab
Author: Lab of Michael J. Guertin
Author-email: guertin@uchc.edu
License: MIT
Requires-Dist: Click
Requires-Dist: pandas
Requires-Dist: configparser
Requires-Dist: PyYAML
Requires-Dist: tqdm
Requires-Dist: numpy
Requires-Dist: scipy
Requires-Dist: matplotlib
Dynamic: author
Dynamic: author-email
Dynamic: description
Dynamic: description-content-type
Dynamic: home-page
Dynamic: license
Dynamic: requires-dist
Dynamic: summary
